gcve/__init__.py
gcve/cli.py
gcve/gna.py
gcve/main.py
gcve/py.typed
gcve/registry.py
gcve/utils.py
gcve-0.12.0.dist-info/METADATA
gcve-0.12.0.dist-info/WHEEL
gcve-0.12.0.dist-info/entry_points.txt
gcve-0.12.0.dist-info/licenses/COPYING
gcve-0.12.0.dist-info/RECORD
